LICENSE
MANIFEST.in
README.rst
setup.py
capitalize_name/__init__.py
capitalize_name/cli.py
capitalize_name.egg-info/PKG-INFO
capitalize_name.egg-info/SOURCES.txt
capitalize_name.egg-info/dependency_links.txt
capitalize_name.egg-info/entry_points.txt
capitalize_name.egg-info/requires.txt
capitalize_name.egg-info/top_level.txt