Metadata-Version: 1.1
Name: capitalize-name
Version: 1.0.1
Summary: Returns the correct writing of a compound name, respecting the first letters of the names in upper case.
Home-page: https://github.com/sxslex/capitalize-name
Author: SleX
Author-email: sx.slex@gmail.com
License: UNKNOWN
Download-URL: https://github.com/sxslex/capitalize-name/archive/v1.0.1.tar.gz
Keywords: capitalize,name,compound name,upper
Platform: UNKNOWN
Classifier: License :: OSI Approved :: GNU General Public License (GPL)
Classifier: Natural Language :: English
Classifier: Operating System :: OS Independent
Classifier: Programming Language :: Python :: 2.6
Classifier: Programming Language :: Python :: 2.7
Classifier: Programming Language :: Python :: 3.3
Classifier: Programming Language :: Python :: 3.4
Classifier: Programming Language :: Python :: 3.5
Classifier: Programming Language :: Python :: 3.6
Classifier: Topic :: Software Development :: Libraries :: Python Modules
